douyin_mcp_server/__init__.py
douyin_mcp_server/__main__.py
douyin_mcp_server/server.py
douyin_mcp_server/config/__init__.py
douyin_mcp_server/config/settings.py
douyin_mcp_server/resources/__init__.py
douyin_mcp_server/resources/douyin_resources.py
douyin_mcp_server/resources/xiaohongshu_resources.py
douyin_mcp_server/services/__init__.py
douyin_mcp_server/services/douyin_service.py
douyin_mcp_server/services/xiaohongshu_service.py
douyin_mcp_server/tools/__init__.py
douyin_mcp_server/tools/douyin_tools.py
douyin_mcp_server/tools/xiaohongshu_tools.py
douyin_mcp_server/utils/__init__.py
douyin_mcp_server/utils/http_client.py
douyin_mcp_server/utils/watermark.py
dy_xhs_mcp_server-1.3.5.dist-info/METADATA
dy_xhs_mcp_server-1.3.5.dist-info/WHEEL
dy_xhs_mcp_server-1.3.5.dist-info/entry_points.txt
dy_xhs_mcp_server-1.3.5.dist-info/licenses/LICENSE
dy_xhs_mcp_server-1.3.5.dist-info/RECORD
